afterburner/__init__.py
afterburner/api.py
afterburner/middleware.py
afterburner/response.py
afterburner-0.0.2.dist-info/METADATA
afterburner-0.0.2.dist-info/WHEEL
afterburner-0.0.2.dist-info/top_level.txt
afterburner-0.0.2.dist-info/RECORD
