Metadata-Version: 2.1
Name: afterburner
Version: 0.0.2
Summary: Afterburner Python Web Framework built for learning purposes.
Home-page: UNKNOWN
Author: 
Author-email: 
License: MIT
Platform: UNKNOWN
Classifier: Programming Language :: Python :: 3.7
Requires-Python: >=3.7.0
Requires-Dist: Jinja2 (==2.10.3)
Requires-Dist: WebOb (==1.8.5)
Requires-Dist: parse (==1.13.0)
Requires-Dist: requests-wsgi-adapter (==0.4.1)
Requires-Dist: requests (==2.22.0)
Requires-Dist: whitenoise (==5.0.1)
